gindex/__init__.py
gindex-0.4.0.dist-info/WHEEL
gindex-0.4.0.dist-info/entry_points.txt
gindex-0.4.0.dist-info/METADATA
gindex-0.4.0.dist-info/RECORD
