Metadata-Version: 2.3
Name: gindex
Version: 0.4.0
Summary: Google Drive index builder
Author: Rémi Duraffort
Author-email: Rémi Duraffort <remi.duraffort@linaro.org>
Requires-Dist: gdown>=5.2.1
Requires-Python: >=3.11
